<?xml version="1.0" encoding="ISO-8859-1"?>

<!DOCTYPE form SYSTEM 'http://www.iam.unibe.ch/~fki/iamdb/form-metadata.dtd'>

<form created="2002-01-14" height="3542" id="a01-011x" last-modified="2002-07-17" skew="-63" status="final" version="3.0_beta" width="2479" writer-id="006">
  <machine-printed-part>
    <machine-print-line text="Delegates from Mr. Kenneth Kaunda&apos;s United National Independence Party (280,000" />
    <machine-print-line text="members) and Mr. Harry Nkumbula&apos;s African National Congress (400,000) will meet" />
    <machine-print-line text="in London today to discuss a common course of action. Sir Roy is violently opposed to" />
    <machine-print-line text="Africans getting an elected majority in Northern Rhodesia, but the Colonial Secretary," />
    <machine-print-line text="Mr. Iain Macleod, is insisting on a policy of change." />
  </machine-printed-part>
  <handwritten-part>
    <line ass="537" asx="0" asy="729" character-width="999" dss="537" dsx="0" dsy="871" fd0="14652" fd1="3154" fd2="-987" filter-width="3" id="a01-011x-00" lbs="654" lbx="0" lby="814" segmentation="err" slant="68000" stroke-width="5057" threshold="168" text="Delegates from Mr. Kenneth Kaunda&apos;s United" ubs="304" ubx="0" uby="764">
      <word id="a01-011x-00-00" sentence-start="yes" tag="NNS" text="Delegates">
        <cmp x="344" y="739" width="45" height="13" />
        <cmp x="346" y="750" width="68" height="65" />
        <cmp x="372" y="778" width="5" height="21" />
        <cmp x="374" y="756" width="5" height="20" />
        <cmp x="412" y="746" width="72" height="56" />
        <cmp x="478" y="765" width="34" height="39" />
        <cmp x="489" y="762" width="64" height="106" />
        <cmp x="557" y="761" width="37" height="42" />
        <cmp x="602" y="740" width="84" height="59" />
      </word>
      <word id="a01-011x-00-01" tag="IN" text="from">
        <cmp x="735" y="734" width="64" height="121" />
        <cmp x="793" y="759" width="110" height="47" />
      </word>
      <word id="a01-011x-00-02" tag="NPT" text="Mr.">
        <cmp x="961" y="720" width="40" height="88" />
        <cmp x="998" y="735" width="19" height="69" />
        <cmp x="1020" y="759" width="28" height="44" />
        <cmp x="1046" y="796" width="8" height="8" />
      </word>
      <word id="a01-011x-00-03" tag="NP" text="Kenneth">
        <cmp x="1124" y="735" width="66" height="71" />
        <cmp x="1188" y="758" width="49" height="48" />
        <cmp x="1233" y="760" width="66" height="50" />
        <cmp x="1305" y="730" width="67" height="79" />
      </word>
      <word id="a01-011x-00-04" tag="NP$" text="Kaunda&apos;s">
        <cmp x="1423" y="732" width="64" height="77" />
        <cmp x="1468" y="749" width="48" height="55" />
        <cmp x="1515" y="751" width="31" height="53" />
        <cmp x="1544" y="755" width="19" height="43" />
        <cmp x="1559" y="748" width="7" height="7" />
        <cmp x="1561" y="750" width="26" height="54" />
        <cmp x="1584" y="748" width="25" height="54" />
        <cmp x="1605" y="749" width="37" height="54" />
        <cmp x="1631" y="745" width="28" height="59" />
        <cmp x="1648" y="750" width="44" height="54" />
        <cmp x="1657" y="737" width="6" height="5" />
        <cmp x="1702" y="762" width="38" height="48" />
        <cmp x="1709" y="740" width="13" height="21" />
      </word>
      <word id="a01-011x-00-05" tag="JJ" text="United">
        <cmp x="1795" y="734" width="32" height="76" />
        <cmp x="1826" y="738" width="41" height="67" />
        <cmp x="1852" y="730" width="8" height="7" />
        <cmp x="1864" y="756" width="7" height="8" />
        <cmp x="1867" y="767" width="5" height="6" />
        <cmp x="1868" y="756" width="21" height="44" />
        <cmp x="1894" y="758" width="24" height="46" />
        <cmp x="1920" y="730" width="8" height="11" />
        <cmp x="1921" y="720" width="49" height="80" />
        <cmp x="1958" y="739" width="67" height="64" />
      </word>
      <lower-contour>
        <point x="353" y="845" />
        <point x="495" y="868" />
        <point x="592" y="844" />
        <point x="750" y="855" />
        <point x="840" y="811" />
        <point x="2027" y="811" />
      </lower-contour>
    </line>
    <line ass="931" asx="0" asy="840" character-width="999" dss="931" dsx="0" dsy="971" fd0="14453" fd1="2966" fd2="-1243" filter-width="3" id="a01-011x-01" lbs="971" lbx="0" lby="924" segmentation="err" slant="71000" stroke-width="5128" threshold="168" text="National Independence Party (280,000 members)" ubs="851" ubx="0" uby="877">
      <word id="a01-011x-01-00" tag="JJ" text="National">
        <cmp x="355" y="849" width="49" height="68" />
        <cmp x="406" y="860" width="36" height="50" />
        <cmp x="447" y="847" width="21" height="64" />
        <cmp x="472" y="874" width="14" height="41" />
        <cmp x="481" y="851" width="7" height="9" />
        <cmp x="496" y="870" width="76" height="41" />
        <cmp x="577" y="847" width="80" height="62" />
      </word>
      <word id="a01-011x-01-01" tag="NN" text="Independence">
        <cmp x="727" y="853" width="15" height="62" />
        <cmp x="749" y="866" width="38" height="48" />
        <cmp x="794" y="859" width="33" height="53" />
        <cmp x="824" y="849" width="43" height="64" />
        <cmp x="873" y="871" width="20" height="61" />
        <cmp x="889" y="864" width="35" height="53" />
        <cmp x="894" y="875" width="5" height="6" />
        <cmp x="921" y="862" width="44" height="46" />
        <cmp x="964" y="865" width="38" height="49" />
        <cmp x="1008" y="852" width="120" height="59" />
        <cmp x="1132" y="864" width="61" height="50" />
      </word>
      <word id="a01-011x-01-02" tag="NN" text="Party">
        <cmp x="1226" y="820" width="70" height="96" />
        <cmp x="1273" y="859" width="61" height="52" />
        <cmp x="1340" y="864" width="50" height="48" />
        <cmp x="1389" y="838" width="38" height="72" />
        <cmp x="1409" y="856" width="71" height="94" />
      </word>
      <word id="a01-011x-01-03" tag="(" text="(">
        <cmp x="1522" y="837" width="28" height="77" />
      </word>
      <word id="a01-011x-01-04" tag="CD" text="280,000">
        <cmp x="1565" y="840" width="39" height="65" />
        <cmp x="1613" y="841" width="75" height="65" />
        <cmp x="1709" y="846" width="9" height="21" />
        <cmp x="1716" y="848" width="50" height="54" />
        <cmp x="1766" y="844" width="46" height="51" />
        <cmp x="1815" y="837" width="36" height="60" />
      </word>
      <word id="a01-011x-01-05" tag="NNS" text="members">
        <cmp x="1903" y="849" width="57" height="46" />
        <cmp x="1958" y="845" width="38" height="43" />
        <cmp x="1989" y="841" width="30" height="46" />
        <cmp x="2004" y="843" width="43" height="43" />
        <cmp x="2019" y="848" width="3" height="4" />
      </word>
      <word id="a01-011x-01-06" tag=")" text=")">
        <cmp x="2045" y="819" width="75" height="65" />
        <cmp x="2116" y="840" width="50" height="39" />
        <cmp x="2152" y="819" width="42" height="85" />
      </word>
      <upper-contour>
        <point x="353" y="845" />
        <point x="495" y="868" />
        <point x="592" y="844" />
        <point x="750" y="855" />
        <point x="840" y="811" />
        <point x="2027" y="811" />
      </upper-contour>
      <lower-contour>
        <point x="353" y="932" />
        <point x="997" y="916" />
        <point x="1409" y="950" />
        <point x="1502" y="914" />
        <point x="2110" y="914" />
      </lower-contour>
    </line>
    <line ass="324" asx="0" asy="935" character-width="999" dss="324" dsx="0" dsy="1043" fd0="14322" fd1="2963" fd2="-1334" filter-width="3" id="a01-011x-02" lbs="267" lbx="0" lby="1007" segmentation="err" slant="71000" stroke-width="5184" threshold="165" text="and Mr. Harry Nkumbula&apos;s African National" ubs="439" ubx="0" uby="962">
      <word id="a01-011x-02-00" tag="CC" text="and">
        <cmp x="344" y="954" width="67" height="53" />
        <cmp x="412" y="964" width="10" height="40" />
        <cmp x="426" y="948" width="46" height="61" />
      </word>
      <word id="a01-011x-02-01" tag="NPT" text="Mr.">
        <cmp x="576" y="936" width="34" height="75" />
        <cmp x="610" y="947" width="17" height="53" />
        <cmp x="633" y="961" width="29" height="42" />
        <cmp x="662" y="989" width="7" height="7" />
      </word>
      <word id="a01-011x-02-02" tag="NP" text="Harry">
        <cmp x="720" y="940" width="48" height="70" />
        <cmp x="763" y="949" width="43" height="51" />
        <cmp x="808" y="956" width="58" height="47" />
        <cmp x="860" y="955" width="58" height="72" />
      </word>
      <word id="a01-011x-02-03" tag="NP$" text="Nkumbula&apos;s">
        <cmp x="975" y="932" width="63" height="70" />
        <cmp x="995" y="1006" width="5" height="7" />
        <cmp x="1038" y="931" width="46" height="67" />
        <cmp x="1078" y="957" width="29" height="45" />
        <cmp x="1107" y="954" width="27" height="45" />
        <cmp x="1127" y="959" width="26" height="42" />
        <cmp x="1143" y="962" width="43" height="42" />
        <cmp x="1187" y="932" width="45" height="69" />
        <cmp x="1232" y="955" width="20" height="49" />
        <cmp x="1263" y="934" width="51" height="69" />
        <cmp x="1299" y="948" width="40" height="56" />
        <cmp x="1358" y="951" width="36" height="59" />
        <cmp x="1362" y="935" width="13" height="29" />
      </word>
      <word id="a01-011x-02-04" tag="JNP" text="African">
        <cmp x="1443" y="934" width="68" height="78" />
        <cmp x="1511" y="928" width="50" height="107" />
        <cmp x="1549" y="961" width="42" height="51" />
        <cmp x="1605" y="935" width="6" height="10" />
        <cmp x="1607" y="959" width="39" height="45" />
        <cmp x="1641" y="957" width="70" height="43" />
        <cmp x="1712" y="968" width="17" height="31" />
      </word>
      <word id="a01-011x-02-05" tag="JJ" text="National">
        <cmp x="1786" y="933" width="64" height="65" />
        <cmp x="1840" y="943" width="38" height="50" />
        <cmp x="1882" y="933" width="43" height="66" />
        <cmp x="1931" y="952" width="81" height="44" />
        <cmp x="1935" y="928" width="7" height="8" />
        <cmp x="2015" y="933" width="94" height="63" />
      </word>
      <upper-contour>
        <point x="353" y="932" />
        <point x="997" y="916" />
        <point x="1409" y="950" />
        <point x="1502" y="914" />
        <point x="2110" y="914" />
      </upper-contour>
      <lower-contour>
        <point x="342" y="1012" />
        <point x="857" y="1032" />
        <point x="996" y="1012" />
        <point x="1511" y="1035" />
        <point x="1883" y="999" />
        <point x="2055" y="999" />
      </lower-contour>
    </line>
    <line ass="166" asx="0" asy="1016" character-width="999" dss="166" dsx="0" dsy="1175" fd0="14484" fd1="3064" fd2="-1061" filter-width="3" id="a01-011x-03" lbs="153" lbx="0" lby="1103" segmentation="err" slant="74000" stroke-width="5057" threshold="168" text="Congress (400,000) will meet in London today" ubs="192" ubx="0" uby="1059">
      <word id="a01-011x-03-00" tag="NN" text="Congress">
        <cmp x="336" y="1031" width="116" height="69" />
        <cmp x="455" y="1052" width="55" height="123" />
        <cmp x="516" y="1065" width="60" height="53" />
        <cmp x="571" y="1067" width="26" height="43" />
        <cmp x="591" y="1069" width="22" height="39" />
      </word>
      <word id="a01-011x-03-01" tag="(" text="(">
        <cmp x="678" y="1042" width="29" height="72" />
      </word>
      <word id="a01-011x-03-02" tag="CD" text="400,000">
        <cmp x="722" y="1042" width="33" height="73" />
        <cmp x="763" y="1047" width="37" height="56" />
        <cmp x="797" y="1047" width="34" height="60" />
        <cmp x="851" y="1048" width="10" height="17" />
        <cmp x="860" y="1047" width="37" height="57" />
        <cmp x="897" y="1034" width="77" height="66" />
        <cmp x="962" y="1015" width="42" height="94" />
      </word>
      <word id="a01-011x-03-03" tag=")" text=")">
        <cmp x="1038" y="1042" width="72" height="54" />
      </word>
      <word id="a01-011x-03-04" tag="MD" text="will">
        <cmp x="1113" y="1027" width="4" height="8" />
        <cmp x="1119" y="1018" width="26" height="73" />
        <cmp x="1136" y="1026" width="27" height="73" />
      </word>
      <word id="a01-011x-03-05" tag="VB" text="meet">
        <cmp x="1204" y="1047" width="119" height="55" />
        <cmp x="1329" y="1025" width="37" height="72" />
      </word>
      <word id="a01-011x-03-06" tag="IN" text="in">
        <cmp x="1425" y="1057" width="63" height="44" />
        <cmp x="1441" y="1029" width="16" height="9" />
      </word>
      <word id="a01-011x-03-07" tag="NP" text="London">
        <cmp x="1570" y="1038" width="26" height="68" />
        <cmp x="1594" y="1053" width="70" height="48" />
        <cmp x="1663" y="1046" width="54" height="57" />
        <cmp x="1706" y="1055" width="70" height="47" />
      </word>
      <word id="a01-011x-03-08" tag="NR" text="today">
        <cmp x="1864" y="1033" width="24" height="69" />
        <cmp x="1887" y="1042" width="38" height="58" />
        <cmp x="1924" y="1038" width="44" height="58" />
        <cmp x="1959" y="1046" width="40" height="50" />
        <cmp x="1988" y="1051" width="24" height="44" />
        <cmp x="2018" y="1061" width="14" height="31" />
        <cmp x="2032" y="1062" width="22" height="57" />
      </word>
      <upper-contour>
        <point x="342" y="1012" />
        <point x="857" y="1032" />
        <point x="996" y="1012" />
        <point x="1511" y="1035" />
        <point x="1883" y="999" />
        <point x="2055" y="999" />
      </upper-contour>
      <lower-contour>
        <point x="345" y="1142" />
        <point x="456" y="1176" />
        <point x="511" y="1118" />
        <point x="2037" y="1118" />
      </lower-contour>
    </line>
    <line ass="852" asx="0" asy="1143" character-width="999" dss="852" dsx="0" dsy="1244" fd0="14074" fd1="2904" fd2="-1317" filter-width="3" id="a01-011x-04" lbs="966" lbx="0" lby="1219" segmentation="err" slant="71000" stroke-width="5141" threshold="168" text="to discuss a common course of action." ubs="626" ubx="0" uby="1171">
      <word id="a01-011x-04-00" tag="TO" text="to">
        <cmp x="347" y="1149" width="35" height="64" />
        <cmp x="383" y="1159" width="33" height="52" />
      </word>
      <word id="a01-011x-04-01" tag="VB" text="discuss">
        <cmp x="505" y="1146" width="55" height="65" />
        <cmp x="562" y="1166" width="13" height="43" />
        <cmp x="577" y="1135" width="10" height="10" />
        <cmp x="582" y="1155" width="34" height="56" />
        <cmp x="619" y="1160" width="36" height="47" />
        <cmp x="658" y="1166" width="19" height="42" />
        <cmp x="682" y="1168" width="13" height="43" />
        <cmp x="695" y="1162" width="66" height="52" />
      </word>
      <word id="a01-011x-04-02" tag="AT" text="a">
        <cmp x="839" y="1163" width="37" height="48" />
      </word>
      <word id="a01-011x-04-03" tag="JJ" text="common">
        <cmp x="934" y="1155" width="38" height="46" />
        <cmp x="971" y="1154" width="68" height="48" />
        <cmp x="1034" y="1158" width="41" height="41" />
        <cmp x="1075" y="1153" width="71" height="49" />
        <cmp x="1141" y="1154" width="85" height="50" />
      </word>
      <word id="a01-011x-04-04" tag="NN" text="course">
        <cmp x="1275" y="1151" width="111" height="46" />
        <cmp x="1390" y="1156" width="37" height="43" />
        <cmp x="1425" y="1154" width="61" height="45" />
      </word>
      <word id="a01-011x-04-05" tag="INO" text="of">
        <cmp x="1545" y="1127" width="81" height="95" />
      </word>
      <word id="a01-011x-04-06" tag="NN" text="action">
        <cmp x="1671" y="1142" width="43" height="44" />
        <cmp x="1715" y="1139" width="39" height="49" />
        <cmp x="1751" y="1130" width="38" height="60" />
        <cmp x="1800" y="1129" width="4" height="9" />
        <cmp x="1803" y="1146" width="95" height="44" />
      </word>
      <word id="a01-011x-04-07" tag="." text=".">
        <cmp x="1936" y="1178" width="8" height="13" />
        <cmp x="1964" y="1121" width="72" height="93" />
      </word>
      <upper-contour>
        <point x="345" y="1142" />
        <point x="456" y="1176" />
        <point x="511" y="1118" />
        <point x="2037" y="1118" />
      </upper-contour>
      <lower-contour>
        <point x="345" y="1222" />
        <point x="1883" y="1222" />
      </lower-contour>
    </line>
    <line ass="-402" asx="0" asy="1226" character-width="999" dss="-402" dsx="0" dsy="1372" fd0="14504" fd1="3118" fd2="-1073" filter-width="3" id="a01-011x-05" lbs="-385" lbx="0" lby="1297" segmentation="err" slant="72000" stroke-width="5083" threshold="170" text="Sir Roy is violently opposed to Africans" ubs="-437" ubx="0" uby="1257">
      <word id="a01-011x-05-00" sentence-start="yes" tag="NPT" text="Sir">
        <cmp x="343" y="1242" width="57" height="69" />
        <cmp x="393" y="1269" width="14" height="43" />
        <cmp x="410" y="1239" width="6" height="14" />
        <cmp x="425" y="1260" width="34" height="53" />
      </word>
      <word id="a01-011x-05-01" tag="NP" text="Roy">
        <cmp x="508" y="1238" width="74" height="74" />
        <cmp x="569" y="1260" width="61" height="46" />
        <cmp x="589" y="1273" width="56" height="105" />
      </word>
      <word id="a01-011x-05-02" tag="BEZ" text="is">
        <cmp x="690" y="1268" width="23" height="46" />
        <cmp x="707" y="1240" width="10" height="9" />
        <cmp x="707" y="1273" width="26" height="44" />
      </word>
      <word id="a01-011x-05-03" tag="RB" text="violently">
        <cmp x="790" y="1266" width="40" height="50" />
        <cmp x="827" y="1267" width="17" height="45" />
        <cmp x="846" y="1259" width="35" height="54" />
        <cmp x="847" y="1240" width="5" height="11" />
        <cmp x="889" y="1238" width="40" height="74" />
        <cmp x="930" y="1267" width="26" height="42" />
        <cmp x="955" y="1263" width="17" height="43" />
        <cmp x="975" y="1245" width="30" height="66" />
        <cmp x="1002" y="1242" width="32" height="62" />
        <cmp x="1034" y="1268" width="26" height="60" />
      </word>
      <word id="a01-011x-05-04" tag="VBN" text="opposed">
        <cmp x="1126" y="1259" width="38" height="50" />
        <cmp x="1152" y="1262" width="58" height="74" />
        <cmp x="1195" y="1260" width="90" height="67" />
        <cmp x="1282" y="1258" width="40" height="50" />
        <cmp x="1315" y="1247" width="82" height="67" />
      </word>
      <word id="a01-011x-05-05" tag="IN" text="to">
        <cmp x="1456" y="1247" width="30" height="61" />
        <cmp x="1483" y="1253" width="38" height="59" />
      </word>
      <word id="a01-011x-05-06" tag="NNPS" text="Africans">
        <cmp x="1578" y="1240" width="75" height="77" />
        <cmp x="1634" y="1238" width="59" height="115" />
        <cmp x="1674" y="1267" width="48" height="46" />
        <cmp x="1729" y="1242" width="7" height="10" />
        <cmp x="1731" y="1254" width="151" height="55" />
      </word>
      <upper-contour>
        <point x="345" y="1222" />
        <point x="1883" y="1222" />
      </upper-contour>
      <lower-contour>
        <point x="341" y="1314" />
        <point x="589" y="1378" />
        <point x="673" y="1327" />
        <point x="1152" y="1336" />
        <point x="1633" y="1354" />
        <point x="1727" y="1309" />
        <point x="1883" y="1309" />
      </lower-contour>
    </line>
    <line ass="-284" asx="0" asy="1324" character-width="999" dss="-284" dsx="0" dsy="1517" fd0="14080" fd1="2495" fd2="-1982" filter-width="3" id="a01-011x-06" lbs="-303" lbx="0" lby="1395" segmentation="err" slant="74000" stroke-width="5120" threshold="165" text="getting an elected majority in Northern" ubs="-246" ubx="0" uby="1361">
      <word id="a01-011x-06-00" tag="VBG" text="getting">
        <cmp x="333" y="1345" width="90" height="176" />
        <cmp x="388" y="1346" width="34" height="59" />
        <cmp x="425" y="1332" width="48" height="71" />
        <cmp x="474" y="1356" width="36" height="49" />
        <cmp x="476" y="1331" width="7" height="10" />
        <cmp x="483" y="1358" width="56" height="125" />
      </word>
      <word id="a01-011x-06-01" tag="AT" text="an">
        <cmp x="667" y="1360" width="58" height="41" />
        <cmp x="713" y="1366" width="21" height="39" />
        <cmp x="734" y="1369" width="20" height="33" />
      </word>
      <word id="a01-011x-06-02" tag="JJ" text="elected">
        <cmp x="806" y="1355" width="91" height="56" />
        <cmp x="874" y="1346" width="13" height="11" />
        <cmp x="899" y="1366" width="39" height="40" />
        <cmp x="938" y="1347" width="47" height="62" />
        <cmp x="976" y="1330" width="62" height="84" />
      </word>
      <word id="a01-011x-06-03" tag="NN" text="majority">
        <cmp x="1106" y="1373" width="55" height="46" />
        <cmp x="1163" y="1370" width="55" height="48" />
        <cmp x="1215" y="1374" width="21" height="46" />
        <cmp x="1238" y="1338" width="7" height="10" />
        <cmp x="1241" y="1364" width="40" height="46" />
        <cmp x="1288" y="1366" width="39" height="43" />
        <cmp x="1334" y="1343" width="7" height="11" />
        <cmp x="1336" y="1341" width="28" height="68" />
        <cmp x="1354" y="1373" width="59" height="65" />
      </word>
      <word id="a01-011x-06-04" tag="IN" text="in">
        <cmp x="1451" y="1376" width="24" height="40" />
        <cmp x="1472" y="1347" width="9" height="7" />
        <cmp x="1473" y="1379" width="35" height="36" />
        <cmp x="1474" y="1387" width="5" height="5" />
      </word>
      <word id="a01-011x-06-05" tag="NP" text="Northern">
        <cmp x="1579" y="1354" width="135" height="64" />
        <cmp x="1705" y="1342" width="39" height="63" />
        <cmp x="1726" y="1344" width="38" height="70" />
        <cmp x="1766" y="1361" width="42" height="42" />
        <cmp x="1812" y="1364" width="84" height="42" />
      </word>
      <upper-contour>
        <point x="341" y="1314" />
        <point x="589" y="1378" />
        <point x="673" y="1327" />
        <point x="1152" y="1336" />
        <point x="1633" y="1354" />
        <point x="1727" y="1309" />
        <point x="1883" y="1309" />
      </upper-contour>
      <lower-contour>
        <point x="420" y="1477" />
        <point x="431" y="1449" />
        <point x="486" y="1480" />
        <point x="502" y="1483" />
        <point x="519" y="1448" />
        <point x="1178" y="1419" />
        <point x="1352" y="1441" />
        <point x="1898" y="1441" />
      </lower-contour>
    </line>
    <line ass="270" asx="0" asy="1427" character-width="999" dss="270" dsx="0" dsy="1622" fd0="14346" fd1="2874" fd2="-1205" filter-width="3" id="a01-011x-07" lbs="374" lbx="0" lby="1532" segmentation="err" slant="74000" stroke-width="5095" threshold="163" text="Rhodesia, but the Colonial Secretary, Mr. Iain" ubs="61" ubx="0" uby="1482">
      <word id="a01-011x-07-00" tag="NP" text="Rhodesia">
        <cmp x="422" y="1457" width="34" height="73" />
        <cmp x="460" y="1479" width="34" height="54" />
        <cmp x="499" y="1470" width="77" height="62" />
        <cmp x="571" y="1479" width="37" height="49" />
        <cmp x="607" y="1483" width="19" height="50" />
        <cmp x="621" y="1463" width="9" height="15" />
        <cmp x="629" y="1476" width="33" height="56" />
      </word>
      <word id="a01-011x-07-01" tag="," text=",">
        <cmp x="664" y="1521" width="16" height="35" />
      </word>
      <word id="a01-011x-07-02" tag="CC" text="but">
        <cmp x="721" y="1449" width="60" height="86" />
        <cmp x="776" y="1486" width="21" height="48" />
        <cmp x="798" y="1488" width="23" height="41" />
        <cmp x="823" y="1457" width="32" height="78" />
      </word>
      <word id="a01-011x-07-03" tag="ATI" text="the">
        <cmp x="893" y="1468" width="89" height="67" />
      </word>
      <word id="a01-011x-07-04" tag="JJ" text="Colonial">
        <cmp x="1059" y="1458" width="47" height="72" />
        <cmp x="1093" y="1461" width="79" height="68" />
        <cmp x="1150" y="1422" width="70" height="111" />
        <cmp x="1200" y="1485" width="61" height="50" />
        <cmp x="1262" y="1466" width="6" height="8" />
        <cmp x="1263" y="1465" width="72" height="66" />
      </word>
      <word id="a01-011x-07-05" tag="NPT" text="Secretary">
        <cmp x="1390" y="1460" width="85" height="74" />
        <cmp x="1474" y="1475" width="42" height="51" />
        <cmp x="1522" y="1474" width="74" height="52" />
        <cmp x="1605" y="1459" width="27" height="71" />
        <cmp x="1632" y="1469" width="49" height="51" />
        <cmp x="1661" y="1478" width="81" height="138" />
      </word>
      <word id="a01-011x-07-06" tag="," text=",">
        <cmp x="1754" y="1509" width="16" height="37" />
      </word>
      <word id="a01-011x-07-07" tag="NPT" text="Mr.">
        <cmp x="1850" y="1448" width="48" height="84" />
        <cmp x="1906" y="1481" width="39" height="46" />
        <cmp x="1935" y="1524" width="10" height="8" />
        <cmp x="2005" y="1450" width="30" height="79" />
      </word>
      <word id="a01-011x-07-08" tag="NP" text="Iain">
        <cmp x="2025" y="1474" width="46" height="49" />
        <cmp x="2073" y="1503" width="3" height="4" />
        <cmp x="2075" y="1486" width="20" height="37" />
        <cmp x="2096" y="1482" width="21" height="42" />
        <cmp x="2101" y="1456" width="5" height="14" />
        <cmp x="2121" y="1480" width="24" height="47" />
      </word>
      <upper-contour>
        <point x="420" y="1477" />
        <point x="431" y="1449" />
        <point x="486" y="1480" />
        <point x="502" y="1483" />
        <point x="519" y="1448" />
        <point x="1178" y="1419" />
        <point x="1352" y="1441" />
        <point x="1898" y="1441" />
      </upper-contour>
      <lower-contour>
        <point x="420" y="1556" />
        <point x="1661" y="1616" />
        <point x="1739" y="1546" />
        <point x="1964" y="1546" />
      </lower-contour>
    </line>
    <line ass="207" asx="0" asy="1563" character-width="999" dss="207" dsx="0" dsy="1768" fd0="13762" fd1="2479" fd2="-1482" filter-width="3" id="a01-011x-08" lbs="365" lbx="0" lby="1641" segmentation="ok" slant="71000" stroke-width="5125" threshold="161" text="Macleod, is insisting on a policy of change." ubs="-110" ubx="0" uby="1595">
      <word id="a01-011x-08-00" tag="NP" text="Macleod">
        <cmp x="366" y="1562" width="29" height="85" />
        <cmp x="394" y="1576" width="45" height="67" />
        <cmp x="447" y="1595" width="39" height="54" />
        <cmp x="492" y="1581" width="41" height="62" />
        <cmp x="534" y="1592" width="37" height="51" />
        <cmp x="570" y="1580" width="45" height="64" />
      </word>
      <word id="a01-011x-08-01" tag="," text=",">
        <cmp x="626" y="1635" width="11" height="26" />
      </word>
      <word id="a01-011x-08-02" tag="BEZ" text="is">
        <cmp x="672" y="1600" width="27" height="51" />
        <cmp x="685" y="1569" width="9" height="9" />
        <cmp x="696" y="1602" width="23" height="45" />
      </word>
      <word id="a01-011x-08-03" tag="VBG" text="insisting">
        <cmp x="770" y="1600" width="12" height="44" />
        <cmp x="786" y="1563" width="6" height="10" />
        <cmp x="793" y="1592" width="35" height="50" />
        <cmp x="827" y="1594" width="34" height="51" />
        <cmp x="857" y="1598" width="49" height="53" />
        <cmp x="869" y="1574" width="9" height="8" />
        <cmp x="906" y="1570" width="35" height="76" />
        <cmp x="935" y="1609" width="62" height="117" />
        <cmp x="942" y="1570" width="6" height="7" />
        <cmp x="943" y="1597" width="40" height="50" />
      </word>
      <word id="a01-011x-08-04" tag="IN" text="on">
        <cmp x="1050" y="1595" width="79" height="48" />
      </word>
      <word id="a01-011x-08-05" tag="AT" text="a">
        <cmp x="1179" y="1590" width="40" height="49" />
      </word>
      <word id="a01-011x-08-06" tag="NN" text="policy">
        <cmp x="1271" y="1575" width="124" height="99" />
        <cmp x="1387" y="1601" width="22" height="42" />
        <cmp x="1397" y="1603" width="87" height="137" />
        <cmp x="1407" y="1600" width="39" height="43" />
        <cmp x="1409" y="1582" width="6" height="10" />
        <cmp x="1446" y="1604" width="15" height="30" />
      </word>
      <word id="a01-011x-08-07" tag="INO" text="of">
        <cmp x="1551" y="1574" width="74" height="102" />
      </word>
      <word id="a01-011x-08-08" tag="NN" text="change">
        <cmp x="1737" y="1562" width="83" height="74" />
        <cmp x="1803" y="1586" width="75" height="54" />
        <cmp x="1829" y="1588" width="107" height="174" />
      </word>
      <word id="a01-011x-08-09" tag="." text=".">
        <cmp x="1952" y="1627" width="9" height="11" />
      </word>
      <upper-contour>
        <point x="420" y="1556" />
        <point x="1661" y="1616" />
        <point x="1739" y="1546" />
        <point x="1964" y="1546" />
      </upper-contour>
    </line>
  </handwritten-part>
</form>

