<?xml version="1.0" encoding="ISO-8859-1"?>

<!DOCTYPE form SYSTEM 'http://www.iam.unibe.ch/~fki/iamdb/form-metadata.dtd'>

<form created="2002-01-25" height="3542" id="l07-085" last-modified="2002-07-17" skew="30" status="final" version="3.0_beta" width="2479" writer-id="496">
  <machine-printed-part>
    <machine-print-line text="&amp;quot;And I can&apos;t allow that,&amp;quot; I said. &amp;quot;Deadlock,&amp;quot; said Max. &amp;quot;No, it isn&apos;t. I&apos;m determined" />
    <machine-print-line text="to go, and by myself, whatever you say.&amp;quot; &amp;quot;I was afraid of that.&amp;quot; He sounded resigned" />
    <machine-print-line text="but none the less hopeful. &amp;quot;You&apos;re a very wilful woman but I&apos;ll change your mind for" />
    <machine-print-line text="you one of these days." />
  </machine-printed-part>
  <handwritten-part>
    <line ass="449" asx="0" asy="674" character-width="999" dss="449" dsx="0" dsy="773" fd0="13501" fd1="2668" fd2="-193" filter-width="4" id="l07-085-00" lbs="253" lbx="0" lby="751" segmentation="err" slant="70000" stroke-width="5889" threshold="168" text="&amp;quot;And I can&apos;t allow that,&amp;quot; I said." ubs="841" ubx="0" uby="723">
      <word id="l07-085-00-00" sentence-start="yes" tag="*&apos;" text="&quot;">
        <cmp x="365" y="672" width="20" height="38" />
        <cmp x="394" y="673" width="22" height="37" />
      </word>
      <word id="l07-085-00-01" tag="CC" text="And">
        <cmp x="427" y="687" width="42" height="73" />
        <cmp x="483" y="719" width="39" height="43" />
        <cmp x="534" y="675" width="53" height="88" />
      </word>
      <word id="l07-085-00-02" tag="PP1A" text="I">
        <cmp x="643" y="686" width="65" height="70" />
      </word>
      <word id="l07-085-00-03" tag="MDX" text="can&apos;t">
        <cmp x="768" y="712" width="51" height="47" />
        <cmp x="836" y="707" width="38" height="45" />
        <cmp x="882" y="706" width="39" height="45" />
        <cmp x="947" y="684" width="21" height="29" />
        <cmp x="970" y="674" width="37" height="79" />
        <cmp x="995" y="670" width="4" height="4" />
      </word>
      <word id="l07-085-00-04" tag="VB" text="allow">
        <cmp x="1091" y="713" width="40" height="45" />
        <cmp x="1147" y="676" width="36" height="76" />
        <cmp x="1182" y="671" width="42" height="78" />
        <cmp x="1215" y="719" width="34" height="31" />
        <cmp x="1278" y="712" width="67" height="35" />
      </word>
      <word id="l07-085-00-05" tag="DT" text="that">
        <cmp x="1425" y="682" width="49" height="64" />
        <cmp x="1479" y="669" width="39" height="78" />
        <cmp x="1523" y="707" width="39" height="39" />
        <cmp x="1579" y="666" width="34" height="80" />
        <cmp x="1591" y="725" width="26" height="36" />
      </word>
      <word id="l07-085-00-06" tag="," text=",">
        <cmp x="1666" y="674" width="19" height="30" />
      </word>
      <word id="l07-085-00-07" tag="**&apos;" text="&quot;">
        <cmp x="1693" y="673" width="21" height="36" />
      </word>
      <word id="l07-085-00-08" tag="PP1A" text="I">
        <cmp x="1756" y="675" width="68" height="74" />
      </word>
      <word id="l07-085-00-09" tag="VBD" text="said">
        <cmp x="1869" y="701" width="48" height="45" />
        <cmp x="1918" y="705" width="43" height="43" />
        <cmp x="1969" y="706" width="19" height="42" />
        <cmp x="1991" y="684" width="7" height="8" />
        <cmp x="2004" y="663" width="56" height="87" />
      </word>
      <word id="l07-085-00-10" tag="." text=".">
        <cmp x="2068" y="732" width="10" height="13" />
      </word>
      <lower-contour>
        <point x="365" y="763" />
        <point x="2079" y="763" />
      </lower-contour>
    </line>
    <line ass="832" asx="0" asy="847" character-width="999" dss="832" dsx="0" dsy="974" fd0="13892" fd1="2754" fd2="-553" filter-width="4" id="l07-085-01" lbs="783" lbx="0" lby="939" segmentation="ok" slant="66999" stroke-width="6126" threshold="168" text="&amp;quot;Deadlock,&amp;quot; said Max. &amp;quot;No, it isn&apos;t." ubs="931" ubx="0" uby="902">
      <word id="l07-085-01-00" sentence-start="yes" tag="*&apos;" text="&quot;">
        <cmp x="367" y="856" width="22" height="34" />
        <cmp x="396" y="855" width="22" height="34" />
      </word>
      <word id="l07-085-01-01" tag="NN" text="Deadlock">
        <cmp x="419" y="861" width="69" height="73" />
        <cmp x="487" y="894" width="38" height="37" />
        <cmp x="536" y="895" width="43" height="37" />
        <cmp x="592" y="842" width="56" height="94" />
        <cmp x="659" y="839" width="35" height="99" />
        <cmp x="689" y="887" width="41" height="47" />
        <cmp x="755" y="890" width="31" height="40" />
        <cmp x="789" y="840" width="53" height="92" />
      </word>
      <word id="l07-085-01-02" tag="," text=",">
        <cmp x="833" y="915" width="18" height="39" />
      </word>
      <word id="l07-085-01-03" tag="**&apos;" text="&quot;">
        <cmp x="897" y="865" width="20" height="34" />
        <cmp x="930" y="865" width="19" height="31" />
      </word>
      <word id="l07-085-01-04" tag="VBD" text="said">
        <cmp x="991" y="888" width="42" height="41" />
        <cmp x="1043" y="890" width="43" height="42" />
        <cmp x="1100" y="893" width="18" height="39" />
        <cmp x="1119" y="870" width="11" height="16" />
        <cmp x="1127" y="838" width="67" height="92" />
      </word>
      <word id="l07-085-01-05" tag="NP" text="Max">
        <cmp x="1287" y="855" width="94" height="84" />
        <cmp x="1386" y="893" width="43" height="36" />
        <cmp x="1438" y="885" width="44" height="43" />
      </word>
      <word id="l07-085-01-06" tag="." text=".">
        <cmp x="1493" y="914" width="8" height="11" />
      </word>
      <word id="l07-085-01-07" sentence-start="yes" tag="*&apos;" text="&quot;">
        <cmp x="1591" y="854" width="24" height="31" />
        <cmp x="1630" y="849" width="25" height="33" />
      </word>
      <word id="l07-085-01-08" tag="UH" text="No">
        <cmp x="1660" y="837" width="80" height="94" />
        <cmp x="1728" y="886" width="37" height="38" />
      </word>
      <word id="l07-085-01-09" tag="," text=",">
        <cmp x="1755" y="907" width="26" height="42" />
      </word>
      <word id="l07-085-01-10" tag="PP3" text="it">
        <cmp x="1835" y="875" width="26" height="46" />
        <cmp x="1859" y="836" width="61" height="84" />
        <cmp x="1863" y="853" width="9" height="16" />
      </word>
      <word id="l07-085-01-11" tag="BEZX" text="isn&apos;t">
        <cmp x="1971" y="866" width="26" height="53" />
        <cmp x="1994" y="872" width="39" height="42" />
        <cmp x="1999" y="845" width="8" height="13" />
        <cmp x="2036" y="877" width="31" height="44" />
        <cmp x="2087" y="855" width="18" height="29" />
        <cmp x="2105" y="836" width="53" height="82" />
      </word>
      <word id="l07-085-01-12" tag="." text=".">
        <cmp x="2135" y="904" width="10" height="13" />
      </word>
      <upper-contour>
        <point x="365" y="763" />
        <point x="2079" y="763" />
      </upper-contour>
      <lower-contour>
        <point x="365" y="954" />
        <point x="2159" y="954" />
      </lower-contour>
    </line>
    <line ass="322" asx="0" asy="1014" character-width="999" dss="322" dsx="0" dsy="1135" fd0="13486" fd1="2909" fd2="-259" filter-width="4" id="l07-085-02" lbs="318" lbx="0" lby="1112" segmentation="err" slant="66000" stroke-width="6103" threshold="168" text="I&apos;m determined to go, and by myself," ubs="331" ubx="0" uby="1071">
      <word id="l07-085-02-00" sentence-start="yes" tag="PP1A" text="I">
        <cmp x="361" y="1033" width="52" height="80" />
      </word>
      <word id="l07-085-02-01" tag="BEM" text="&apos;m">
        <cmp x="435" y="1033" width="20" height="32" />
        <cmp x="436" y="1071" width="67" height="40" />
      </word>
      <word id="l07-085-02-02" tag="JJ" text="determined">
        <cmp x="578" y="1031" width="69" height="88" />
        <cmp x="639" y="1068" width="41" height="41" />
        <cmp x="703" y="1022" width="44" height="82" />
        <cmp x="741" y="1062" width="36" height="41" />
        <cmp x="785" y="1064" width="51" height="46" />
        <cmp x="847" y="1064" width="79" height="44" />
        <cmp x="944" y="1064" width="19" height="45" />
        <cmp x="955" y="1034" width="9" height="16" />
        <cmp x="988" y="1067" width="41" height="41" />
        <cmp x="1050" y="1062" width="43" height="42" />
        <cmp x="1105" y="1013" width="50" height="95" />
      </word>
      <word id="l07-085-02-03" tag="TO" text="to">
        <cmp x="1275" y="1025" width="61" height="87" />
        <cmp x="1318" y="1065" width="38" height="41" />
      </word>
      <word id="l07-085-02-04" tag="VB" text="go">
        <cmp x="1421" y="1063" width="49" height="64" />
        <cmp x="1480" y="1065" width="41" height="42" />
        <cmp x="1515" y="1078" width="21" height="42" />
      </word>
      <word id="l07-085-02-05" tag="," text=",">
        <cmp x="1636" y="1065" width="50" height="42" />
      </word>
      <word id="l07-085-02-06" tag="CC" text="and">
        <cmp x="1693" y="1064" width="44" height="39" />
        <cmp x="1753" y="1005" width="60" height="99" />
      </word>
      <word id="l07-085-02-07" tag="IN" text="by">
        <cmp x="1872" y="1025" width="43" height="74" />
        <cmp x="1926" y="1054" width="46" height="64" />
      </word>
      <word id="l07-085-02-08" tag="PPL" text="myself">
        <cmp x="2009" y="1049" width="53" height="43" />
        <cmp x="2067" y="1048" width="38" height="65" />
        <cmp x="2103" y="1040" width="41" height="46" />
        <cmp x="2139" y="1046" width="33" height="42" />
        <cmp x="2176" y="1003" width="25" height="88" />
        <cmp x="2188" y="1010" width="41" height="97" />
      </word>
      <word id="l07-085-02-09" tag="," text=",">
        <cmp x="2218" y="1069" width="9" height="35" />
      </word>
      <upper-contour>
        <point x="365" y="954" />
        <point x="2159" y="954" />
      </upper-contour>
      <lower-contour>
        <point x="361" y="1127" />
        <point x="2230" y="1127" />
      </lower-contour>
    </line>
    <line ass="275" asx="0" asy="1206" character-width="999" dss="275" dsx="0" dsy="1326" fd0="13763" fd1="2429" fd2="-645" filter-width="4" id="l07-085-03" lbs="325" lbx="0" lby="1288" segmentation="ok" slant="70000" stroke-width="6109" threshold="168" text="whatever you say.&amp;quot; &amp;quot;I was afraid of" ubs="175" ubx="0" uby="1245">
      <word id="l07-085-03-00" tag="WDT" text="whatever">
        <cmp x="363" y="1242" width="65" height="48" />
        <cmp x="440" y="1208" width="39" height="86" />
        <cmp x="491" y="1245" width="42" height="47" />
        <cmp x="548" y="1213" width="45" height="76" />
        <cmp x="584" y="1242" width="41" height="44" />
        <cmp x="655" y="1237" width="40" height="50" />
        <cmp x="706" y="1240" width="38" height="39" />
        <cmp x="751" y="1242" width="48" height="39" />
      </word>
      <word id="l07-085-03-01" tag="PP2" text="you">
        <cmp x="894" y="1230" width="62" height="75" />
        <cmp x="959" y="1244" width="38" height="38" />
        <cmp x="1008" y="1238" width="41" height="47" />
      </word>
      <word id="l07-085-03-02" tag="VB" text="say">
        <cmp x="1136" y="1231" width="46" height="43" />
        <cmp x="1189" y="1238" width="38" height="41" />
        <cmp x="1234" y="1233" width="53" height="63" />
      </word>
      <word id="l07-085-03-03" tag="." text=".">
        <cmp x="1286" y="1267" width="10" height="14" />
      </word>
      <word id="l07-085-03-04" tag="**&apos;" text="&quot;">
        <cmp x="1366" y="1210" width="24" height="39" />
        <cmp x="1394" y="1210" width="22" height="39" />
      </word>
      <word id="l07-085-03-05" sentence-start="yes" tag="*&apos;" text="&quot;">
        <cmp x="1499" y="1211" width="29" height="34" />
        <cmp x="1534" y="1212" width="22" height="33" />
      </word>
      <word id="l07-085-03-06" tag="PP1A" text="I">
        <cmp x="1555" y="1215" width="44" height="78" />
        <cmp x="1575" y="1206" width="49" height="8" />
      </word>
      <word id="l07-085-03-07" tag="BEDZ" text="was">
        <cmp x="1671" y="1249" width="67" height="42" />
        <cmp x="1751" y="1248" width="37" height="43" />
        <cmp x="1790" y="1245" width="39" height="43" />
      </word>
      <word id="l07-085-03-08" tag="JJ" text="afraid">
        <cmp x="1904" y="1242" width="40" height="43" />
        <cmp x="1953" y="1197" width="48" height="88" />
        <cmp x="1977" y="1247" width="37" height="38" />
        <cmp x="2008" y="1240" width="47" height="47" />
        <cmp x="2064" y="1244" width="20" height="43" />
        <cmp x="2092" y="1212" width="9" height="14" />
        <cmp x="2094" y="1196" width="53" height="83" />
      </word>
      <word id="l07-085-03-09" tag="INO" text="of">
        <cmp x="2170" y="1232" width="40" height="55" />
        <cmp x="2197" y="1199" width="53" height="118" />
      </word>
      <upper-contour>
        <point x="361" y="1127" />
        <point x="2230" y="1127" />
      </upper-contour>
      <lower-contour>
        <point x="363" y="1317" />
        <point x="2242" y="1317" />
      </lower-contour>
    </line>
    <line ass="808" asx="0" asy="1382" character-width="999" dss="808" dsx="0" dsy="1489" fd0="13518" fd1="2604" fd2="-553" filter-width="4" id="l07-085-04" lbs="842" lbx="0" lby="1476" segmentation="ok" slant="70000" stroke-width="6194" threshold="168" text="that.&amp;quot; He sounded resigned but none" ubs="740" ubx="0" uby="1429">
      <word id="l07-085-04-00" tag="DT" text="that">
        <cmp x="365" y="1401" width="61" height="72" />
        <cmp x="413" y="1392" width="39" height="80" />
        <cmp x="464" y="1430" width="38" height="43" />
        <cmp x="517" y="1383" width="48" height="89" />
      </word>
      <word id="l07-085-04-01" tag="." text=".">
        <cmp x="559" y="1453" width="10" height="16" />
      </word>
      <word id="l07-085-04-02" tag="**&apos;" text="&quot;">
        <cmp x="637" y="1389" width="21" height="39" />
        <cmp x="662" y="1390" width="20" height="33" />
      </word>
      <word id="l07-085-04-03" sentence-start="yes" tag="PP3A" text="He">
        <cmp x="729" y="1382" width="75" height="91" />
        <cmp x="805" y="1414" width="39" height="42" />
      </word>
      <word id="l07-085-04-04" tag="VBD" text="sounded">
        <cmp x="916" y="1407" width="45" height="52" />
        <cmp x="967" y="1414" width="34" height="43" />
        <cmp x="1007" y="1412" width="37" height="45" />
        <cmp x="1053" y="1417" width="44" height="40" />
        <cmp x="1118" y="1366" width="57" height="95" />
        <cmp x="1175" y="1410" width="35" height="45" />
        <cmp x="1224" y="1366" width="54" height="92" />
      </word>
      <word id="l07-085-04-05" tag="JJ" text="resigned">
        <cmp x="1345" y="1412" width="54" height="46" />
        <cmp x="1397" y="1405" width="43" height="49" />
        <cmp x="1445" y="1408" width="44" height="45" />
        <cmp x="1498" y="1417" width="21" height="40" />
        <cmp x="1521" y="1392" width="9" height="14" />
        <cmp x="1525" y="1405" width="49" height="63" />
        <cmp x="1582" y="1409" width="48" height="44" />
        <cmp x="1641" y="1408" width="35" height="42" />
        <cmp x="1704" y="1366" width="56" height="94" />
      </word>
      <word id="l07-085-04-06" tag="CC" text="but">
        <cmp x="1830" y="1374" width="41" height="76" />
        <cmp x="1886" y="1408" width="37" height="45" />
        <cmp x="1937" y="1366" width="42" height="85" />
      </word>
      <word id="l07-085-04-07" tag="RB31" text="none">
        <cmp x="2021" y="1401" width="43" height="44" />
        <cmp x="2076" y="1398" width="39" height="45" />
        <cmp x="2138" y="1396" width="51" height="49" />
        <cmp x="2199" y="1397" width="42" height="44" />
      </word>
      <upper-contour>
        <point x="363" y="1317" />
        <point x="2242" y="1317" />
      </upper-contour>
      <lower-contour>
        <point x="379" y="1473" />
        <point x="2205" y="1473" />
      </lower-contour>
    </line>
    <line ass="553" asx="0" asy="1555" character-width="999" dss="553" dsx="0" dsy="1671" fd0="13493" fd1="2618" fd2="112" filter-width="4" id="l07-085-05" lbs="610" lbx="0" lby="1644" segmentation="ok" slant="65000" stroke-width="6154" threshold="165" text="the less hopeful. &amp;quot;You&apos;re a very" ubs="440" ubx="0" uby="1602">
      <word id="l07-085-05-00" tag="RB32" text="the">
        <cmp x="381" y="1572" width="46" height="78" />
        <cmp x="437" y="1571" width="39" height="81" />
        <cmp x="487" y="1608" width="35" height="38" />
      </word>
      <word id="l07-085-05-01" tag="RB33" text="less">
        <cmp x="624" y="1561" width="50" height="86" />
        <cmp x="670" y="1601" width="39" height="37" />
        <cmp x="729" y="1594" width="49" height="36" />
        <cmp x="794" y="1592" width="47" height="41" />
      </word>
      <word id="l07-085-05-02" tag="JJ" text="hopeful">
        <cmp x="974" y="1558" width="49" height="80" />
        <cmp x="1028" y="1593" width="36" height="40" />
        <cmp x="1055" y="1589" width="68" height="73" />
        <cmp x="1138" y="1588" width="37" height="35" />
        <cmp x="1206" y="1544" width="62" height="86" />
        <cmp x="1272" y="1578" width="23" height="46" />
        <cmp x="1295" y="1582" width="17" height="42" />
        <cmp x="1324" y="1544" width="40" height="83" />
      </word>
      <word id="l07-085-05-03" tag="." text=".">
        <cmp x="1355" y="1603" width="9" height="14" />
      </word>
      <word id="l07-085-05-04" sentence-start="yes" tag="*&apos;" text="&quot;">
        <cmp x="1479" y="1549" width="24" height="34" />
        <cmp x="1512" y="1546" width="21" height="33" />
      </word>
      <word id="l07-085-05-05" tag="PP2" text="You">
        <cmp x="1539" y="1548" width="80" height="87" />
        <cmp x="1607" y="1594" width="32" height="34" />
        <cmp x="1649" y="1588" width="40" height="39" />
      </word>
      <word id="l07-085-05-06" tag="BER" text="&apos;re">
        <cmp x="1718" y="1565" width="27" height="28" />
        <cmp x="1731" y="1586" width="48" height="45" />
        <cmp x="1772" y="1587" width="43" height="43" />
      </word>
      <word id="l07-085-05-07" tag="AT" text="a">
        <cmp x="1900" y="1585" width="47" height="44" />
      </word>
      <word id="l07-085-05-08" tag="QL" text="very">
        <cmp x="2004" y="1585" width="33" height="42" />
        <cmp x="2050" y="1585" width="39" height="41" />
        <cmp x="2106" y="1584" width="37" height="38" />
        <cmp x="2149" y="1579" width="55" height="58" />
      </word>
      <upper-contour>
        <point x="379" y="1473" />
        <point x="2205" y="1473" />
      </upper-contour>
      <lower-contour>
        <point x="398" y="1662" />
        <point x="2169" y="1662" />
      </lower-contour>
    </line>
    <line ass="-29" asx="0" asy="1721" character-width="999" dss="-29" dsx="0" dsy="1840" fd0="13839" fd1="2467" fd2="-216" filter-width="4" id="l07-085-06" lbs="-1" lbx="0" lby="1812" segmentation="ok" slant="65000" stroke-width="6151" threshold="168" text="wilful woman but I&apos;ll change" ubs="-85" ubx="0" uby="1768">
      <word id="l07-085-06-00" tag="JJ" text="wilful">
        <cmp x="400" y="1763" width="70" height="52" />
        <cmp x="485" y="1769" width="14" height="43" />
        <cmp x="501" y="1738" width="12" height="13" />
        <cmp x="522" y="1725" width="37" height="79" />
        <cmp x="552" y="1722" width="71" height="110" />
        <cmp x="616" y="1768" width="19" height="40" />
        <cmp x="641" y="1771" width="12" height="41" />
        <cmp x="673" y="1730" width="49" height="84" />
      </word>
      <word id="l07-085-06-01" tag="NN" text="woman">
        <cmp x="838" y="1772" width="78" height="48" />
        <cmp x="926" y="1781" width="38" height="43" />
        <cmp x="985" y="1779" width="81" height="45" />
        <cmp x="1079" y="1782" width="43" height="40" />
        <cmp x="1143" y="1777" width="43" height="39" />
      </word>
      <word id="l07-085-06-02" tag="CC" text="but">
        <cmp x="1315" y="1730" width="42" height="81" />
        <cmp x="1379" y="1765" width="37" height="46" />
        <cmp x="1431" y="1728" width="43" height="85" />
      </word>
      <word id="l07-085-06-03" tag="PP1A" text="I">
        <cmp x="1565" y="1739" width="52" height="74" />
      </word>
      <word id="l07-085-06-04" tag="MD" text="&apos;ll">
        <cmp x="1639" y="1733" width="25" height="40" />
        <cmp x="1664" y="1783" width="8" height="7" />
        <cmp x="1666" y="1723" width="52" height="85" />
        <cmp x="1703" y="1728" width="52" height="82" />
      </word>
      <word id="l07-085-06-05" tag="VB" text="change">
        <cmp x="1833" y="1764" width="47" height="54" />
        <cmp x="1884" y="1739" width="38" height="74" />
        <cmp x="1928" y="1773" width="39" height="43" />
        <cmp x="1980" y="1770" width="40" height="38" />
        <cmp x="2040" y="1768" width="65" height="74" />
        <cmp x="2122" y="1763" width="46" height="34" />
      </word>
      <upper-contour>
        <point x="398" y="1662" />
        <point x="2169" y="1662" />
      </upper-contour>
      <lower-contour>
        <point x="398" y="1843" />
        <point x="2169" y="1843" />
      </lower-contour>
    </line>
    <line ass="269" asx="0" asy="1898" character-width="999" dss="269" dsx="0" dsy="2018" fd0="13890" fd1="2513" fd2="-235" filter-width="4" id="l07-085-07" lbs="345" lbx="0" lby="1990" segmentation="ok" slant="66999" stroke-width="6075" threshold="168" text="your mind for you one of these" ubs="116" ubx="0" uby="1948">
      <word id="l07-085-07-00" tag="PP$" text="your">
        <cmp x="386" y="1936" width="56" height="74" />
        <cmp x="463" y="1941" width="35" height="36" />
        <cmp x="520" y="1942" width="36" height="39" />
        <cmp x="568" y="1942" width="47" height="37" />
      </word>
      <word id="l07-085-07-01" tag="NN" text="mind">
        <cmp x="725" y="1944" width="74" height="42" />
        <cmp x="818" y="1944" width="18" height="40" />
        <cmp x="840" y="1919" width="11" height="9" />
        <cmp x="853" y="1942" width="46" height="43" />
        <cmp x="918" y="1894" width="62" height="99" />
      </word>
      <word id="l07-085-07-02" tag="IN" text="for">
        <cmp x="1033" y="1899" width="60" height="102" />
        <cmp x="1088" y="1943" width="39" height="40" />
        <cmp x="1140" y="1956" width="50" height="32" />
      </word>
      <word id="l07-085-07-03" tag="PP2" text="you">
        <cmp x="1340" y="1929" width="72" height="84" />
        <cmp x="1414" y="1947" width="37" height="42" />
        <cmp x="1472" y="1936" width="40" height="48" />
      </word>
      <word id="l07-085-07-04" tag="CD1" text="one">
        <cmp x="1603" y="1940" width="39" height="45" />
        <cmp x="1660" y="1944" width="45" height="39" />
        <cmp x="1737" y="1937" width="33" height="36" />
      </word>
      <word id="l07-085-07-05" tag="INO" text="of">
        <cmp x="1879" y="1931" width="43" height="55" />
        <cmp x="1920" y="1894" width="65" height="115" />
      </word>
      <word id="l07-085-07-06" tag="DTS" text="these">
        <cmp x="2015" y="1906" width="45" height="77" />
        <cmp x="2052" y="1916" width="31" height="67" />
        <cmp x="2092" y="1939" width="36" height="39" />
        <cmp x="2134" y="1934" width="45" height="41" />
        <cmp x="2178" y="1940" width="37" height="40" />
      </word>
      <upper-contour>
        <point x="398" y="1843" />
        <point x="2169" y="1843" />
      </upper-contour>
      <lower-contour>
        <point x="392" y="2009" />
        <point x="683" y="2009" />
      </lower-contour>
    </line>
    <line ass="76" asx="0" asy="2098" character-width="999" dss="76" dsx="0" dsy="2201" fd0="14953" fd1="3794" fd2="957" filter-width="4" id="l07-085-08" lbs="1304" lbx="0" lby="2194" segmentation="ok" slant="65000" stroke-width="6200" threshold="165" text="days." ubs="-2380" ubx="0" uby="2123">
      <word id="l07-085-08-00" tag="NNS" text="days">
        <cmp x="394" y="2098" width="77" height="93" />
        <cmp x="478" y="2139" width="42" height="41" />
        <cmp x="529" y="2139" width="55" height="62" />
        <cmp x="598" y="2135" width="49" height="38" />
      </word>
      <word id="l07-085-08-01" tag="." text=".">
        <cmp x="665" y="2165" width="17" height="18" />
      </word>
      <upper-contour>
        <point x="392" y="2009" />
        <point x="683" y="2009" />
      </upper-contour>
    </line>
  </handwritten-part>
</form>

